{
  "hash": "95acbe30",
  "configHash": "b5761bdc",
  "lockfileHash": "4514d4fb",
  "browserHash": "381d3a4a",
  "optimized": {
    "react/jsx-dev-runtime": {
      "src": "../../node_modules/react/jsx-dev-runtime.js",
      "file": "react_jsx-dev-runtime.js",
      "fileHash": "78d50513",
      "needsInterop": true
    },
    "react-dom/client": {
      "src": "../../node_modules/react-dom/client.js",
      "file": "react-dom_client.js",
      "fileHash": "3a7a8694",
      "needsInterop": true
    },
    "react": {
      "src": "../../node_modules/react/index.js",
      "file": "react.js",
      "fileHash": "209d07b2",
      "needsInterop": true
    },
    "lucide-react": {
      "src": "../../node_modules/lucide-react/dist/esm/lucide-react.js",
      "file": "lucide-react.js",
      "fileHash": "b7d3d986",
      "needsInterop": false
    },
    "@supabase/supabase-js": {
      "src": "../../node_modules/@supabase/supabase-js/dist/module/index.js",
      "file": "@supabase_supabase-js.js",
      "fileHash": "904236e1",
      "needsInterop": false
    },
    "zustand": {
      "src": "../../node_modules/zustand/esm/index.mjs",
      "file": "zustand.js",
      "fileHash": "1b7e88e7",
      "needsInterop": false
    },
    "clsx": {
      "src": "../../node_modules/clsx/dist/clsx.mjs",
      "file": "clsx.js",
      "fileHash": "9c9ff358",
      "needsInterop": false
    },
    "tailwind-merge": {
      "src": "../../node_modules/tailwind-merge/dist/bundle-mjs.mjs",
      "file": "tailwind-merge.js",
      "fileHash": "746f3362",
      "needsInterop": false
    },
    "react-router-dom": {
      "src": "../../node_modules/react-router-dom/dist/index.mjs",
      "file": "react-router-dom.js",
      "fileHash": "161146f5",
      "needsInterop": false
    }
  },
  "chunks": {
    "chunk-E5ODL3YF": {
      "file": "chunk-E5ODL3YF.js"
    },
    "chunk-65KY755N": {
      "file": "chunk-65KY755N.js"
    },
    "chunk-V4OQ3NZ2": {
      "file": "chunk-V4OQ3NZ2.js"
    }
  }
}